todopoc/__init__.py
todopoc/Controllers/MasterControl.py
todopoc/Controllers/WebServer.py
todopoc/Controllers/Models/SQLiteDBMS.py
todopoc/Controllers/Models/Temp.db
todopoc/Controllers/Models/ToDo.db
todopoc/Controllers/Models/ToDoData.py
todopoc/Views/wwwRoot/ToDo.html
todopoc/Views/wwwRoot/index.html
todopoc/Views/wwwRoot/CSS/ToDo.css
todopoc/Views/wwwRoot/CSS/index.css
todopoc/Views/wwwRoot/JS/ToDo.js
todopoc/Views/wwwRoot/JS/index.js
todopoc-1.3.dist-info/LICENSE
todopoc-1.3.dist-info/METADATA
todopoc-1.3.dist-info/WHEEL
todopoc-1.3.dist-info/top_level.txt
todopoc-1.3.dist-info/RECORD
