Metadata-Version: 2.1
Name: todopoc
Version: 1.3
Summary: A To-Do app for Proof of various Concepts
Home-page: https://github.com/enygmator/To-Do-PoC
Author: Tarun & Moyank & Vaibhav
Author-email: tarun.aditya.bc@gmail.com
License: Apache license 2.0
Platform: UNKNOWN
Classifier: License :: OSI Approved :: Apache Software License
Classifier: Intended Audience :: Developers
Classifier: Intended Audience :: Education
Classifier: Development Status :: 7 - Inactive
Classifier: Natural Language :: English
Classifier: Programming Language :: Python :: 3
Classifier: Programming Language :: JavaScript
Classifier: Programming Language :: Unix Shell
Classifier: Operating System :: OS Independent
Requires-Python: >=3.6
